GAparsimony/__init__.py
GAparsimony/gaparsimony.py
GAparsimony/lhs/__init__.py
GAparsimony/lhs/base/__init__.py
GAparsimony/lhs/base/geneticLHS.py
GAparsimony/lhs/base/improvedLHS.py
GAparsimony/lhs/base/maximinLHS.py
GAparsimony/lhs/base/optimumLHS.py
GAparsimony/lhs/base/randomLHS.py
GAparsimony/lhs/util/__init__.py
GAparsimony/lhs/util/bclib.py
GAparsimony/lhs/util/utilityLHS.py
GAparsimony/util/__init__.py
GAparsimony/util/complexity.py
GAparsimony/util/config.py
GAparsimony/util/fitness.py
GAparsimony/util/order.py
GAparsimony/util/parsimony_monitor.py
GAparsimony/util/population.py
test/GAParsimony_test.py
test/LHS_test.py
test/__init__.py
test/utilTest.py
GAparsimony-0.0.15.dist-info/LICENSE
GAparsimony-0.0.15.dist-info/METADATA
GAparsimony-0.0.15.dist-info/WHEEL
GAparsimony-0.0.15.dist-info/top_level.txt
GAparsimony-0.0.15.dist-info/RECORD
