Metadata-Version: 2.1
Name: GAparsimony
Version: 0.0.15
Summary: Combines feature selection, model tuning, and parsimonious model selection with GA optimization. GA selection procedure is based on separate cost and complexity evaluations. Therefore, the best individuals are initially sorted by an error fitness function, and afterwards, models with similar costs are rearranged according to modelcomplexity measurement so as to foster models of lesser complexity. The algorithm can be run sequentially or in parallel.
Home-page: https://github.com/misantam/GAparsimony
Author: Millán Santamaría 
Author-email: GAparsimony@gmail.com
Maintainer: Millán Santamaría
Maintainer-email: GAparsimony@gmail.com
License: MIT License
Platform: UNKNOWN
Classifier: Development Status :: 3 - Alpha
Classifier: Intended Audience :: Science/Research
Classifier: Intended Audience :: Developers
Classifier: Topic :: Scientific/Engineering
Classifier: Topic :: Scientific/Engineering :: Artificial Intelligence
Classifier: License :: OSI Approved :: MIT License
Classifier: Programming Language :: Python :: 3
Requires-Python: >=3.7
License-File: LICENSE
Requires-Dist: numpy
Requires-Dist: pandas
Requires-Dist: seaborn
Requires-Dist: matplotlib
Requires-Dist: sklearn
